khive_crystal/.gitkeep
khive_crystal/__init__.py
khive_crystal/crystal_graph.py
khive_crystal/crystal_structure.py
khive_crystal/decompositions.py
khive_crystal/fundamental_khives.py
khive_crystal/integer_hive_graph.py
khive_crystal/khive.py
khive_crystal/khives.py
khive_crystal/tensor_products.py
khive_crystal/utils.py
khive_crystal/view.py
khive_crystal-0.1.0.dist-info/METADATA
khive_crystal-0.1.0.dist-info/WHEEL
khive_crystal-0.1.0.dist-info/RECORD
