Metadata-Version: 2.3
Name: khive-crystal
Version: 0.1.0
Summary: Add your description here
Requires-Python: >=3.11
Requires-Dist: graphviz>=0.20.3
Requires-Dist: plotly>=5.24.1
Requires-Dist: pydantic>=2.9.2
